makros/__init__.py
makros/cli.py
makros/functions.py
makros/macro_creation.py
makros/macros/enum.ebnf
makros/macros/enum.py
makros/macros/macroImport.ebnf
makros/macros/macro_import.py
makros/macros/namespace.mpy
makros/macros/namespaces.ebnf
makros/macros/pyx.py
makros/macros/types.py
makros/macros/utils.py
makros/makros.py
makros/parser.py
makros/registration/.gitignore
makros/registration/macro_def.py
makros/registration/manifest.mpy
makros/registration/resolver.py
makros/tokens.py
makros/utils.py
makros-1.1.1.dist-info/entry_points.txt
makros-1.1.1.dist-info/LICENSE
makros-1.1.1.dist-info/WHEEL
makros-1.1.1.dist-info/METADATA
makros-1.1.1.dist-info/RECORD
