Metadata-Version: 2.1
Name: makros
Version: 1.1.1
Summary: Modify and extend the Python language with (relative) ease
License: GPL-v3.0
Author: trickypr
Author-email: trickypr@icloud.com
Requires-Python: >=3.7,<4.0
Classifier: License :: Other/Proprietary License
Classifier: Programming Language :: Python :: 3
Classifier: Programming Language :: Python :: 3.10
Classifier: Programming Language :: Python :: 3.7
Classifier: Programming Language :: Python :: 3.8
Classifier: Programming Language :: Python :: 3.9
Requires-Dist: rich (>=12.4.4,<13.0.0)
